caic_python/__init__.py
caic_python/__main__.py
caic_python/_args.py
caic_python/client.py
caic_python/definitions.py
caic_python/enums.py
caic_python/errors.py
caic_python/models.py
caic_python/utils.py
caic_python-0.1.10.dist-info/LICENSE
caic_python-0.1.10.dist-info/METADATA
caic_python-0.1.10.dist-info/WHEEL
caic_python-0.1.10.dist-info/top_level.txt
caic_python-0.1.10.dist-info/RECORD
