Metadata-Version: 2.1
Name: caic-python
Version: 0.1.10
Summary: An async Python client for working with Colorado Avalanche Information Center data.
Author: John Gorman
License: MIT License
Project-URL: Homepage, https://github.com/gormaniac/caic-python
Project-URL: Documentation, https://github.com/gormaniac/caic-python
Requires-Python: >=3.10
License-File: LICENSE
Requires-Dist: aiohttp (==3.8.4)
Requires-Dist: pydantic (==2.0a4)
Requires-Dist: python-dateutil (==2.8.*)
